mermaidpix/__init__.py
mermaidpix/file_processor.py
mermaidpix/logger.py
mermaidpix/main.py
mermaidpix/mermaid_converter.py
mermaidpix-0.7.3.dist-info/METADATA
mermaidpix-0.7.3.dist-info/WHEEL
mermaidpix-0.7.3.dist-info/entry_points.txt
mermaidpix-0.7.3.dist-info/RECORD
