Metadata-Version: 2.1
Name: mermaidpix
Version: 0.7.3
Summary: A tool for converting Mermaid diagrams in Markdown to high-res PNG images
License: MIT
Author: Raphaël MANSUY
Author-email: raphael.mansuy@gmail.com
Requires-Python: >=3.12,<4.0
Classifier: License :: OSI Approved :: MIT License
Classifier: Programming Language :: Python :: 3
Classifier: Programming Language :: Python :: 3.12
Requires-Dist: click (>=8.1.7,<9.0.0)
